mlflow_secrets_auth/__init__.py
mlflow_secrets_auth/base.py
mlflow_secrets_auth/cache.py
mlflow_secrets_auth/cli.py
mlflow_secrets_auth/config.py
mlflow_secrets_auth/constants.py
mlflow_secrets_auth/messages.py
mlflow_secrets_auth/providers/__init__.py
mlflow_secrets_auth/providers/aws_secrets_manager.py
mlflow_secrets_auth/providers/azure_key_vault.py
mlflow_secrets_auth/providers/vault.py
mlflow_secrets_auth/utils.py
mlflow_secrets_auth-0.2.0.dist-info/LICENSE
mlflow_secrets_auth-0.2.0.dist-info/METADATA
mlflow_secrets_auth-0.2.0.dist-info/WHEEL
mlflow_secrets_auth-0.2.0.dist-info/entry_points.txt
mlflow_secrets_auth-0.2.0.dist-info/RECORD
