Metadata-Version: 2.3
Name: mlflow-secrets-auth
Version: 0.2.0
Summary: MLflow plugin that injects authentication headers from secret managers
License: Apache-2.0
Keywords: mlflow,authentication,secrets,vault,aws,azure
Author: Hugo Carvalho
Author-email: hugodanielsilvacarvalho.hc@gmail.com
Requires-Python: >=3.9,<4.0
Classifier: Development Status :: 3 - Alpha
Classifier: Intended Audience :: Developers
Classifier: License :: OSI Approved :: Apache Software License
Classifier: Programming Language :: Python :: 3
Classifier: Programming Language :: Python :: 3.9
Classifier: Programming Language :: Python :: 3.10
Classifier: Programming Language :: Python :: 3.11
Classifier: Programming Language :: Python :: 3.12
Classifier: Programming Language :: Python :: 3.13
Classifier: Topic :: Software Development :: Libraries :: Python Modules
Classifier: Topic :: System :: Systems Administration :: Authentication/Directory
Provides-Extra: aws
Provides-Extra: azure
Provides-Extra: vault
Requires-Dist: azure-identity (>=1.24.0) ; extra == "azure"
Requires-Dist: azure-keyvault-secrets (>=4.10.0) ; extra == "azure"
Requires-Dist: boto3 (>=1.40.11) ; extra == "aws"
Requires-Dist: hvac (>=2.3.0) ; extra == "vault"
Requires-Dist: mlflow-skinny (>=2.20.4,<4.0)
